nonebot_plugin_tcping-1.1.6.dist-info/METADATA
nonebot_plugin_tcping-1.1.6.dist-info/WHEEL
nonebot_plugin_tcping-1.1.6.dist-info/entry_points.txt
nonebot_plugin_tcping/__init__.py
nonebot_plugin_tcping/config.py
nonebot_plugin_tcping-1.1.6.dist-info/RECORD
