Metadata-Version: 2.1
Name: nonebot-plugin-tcping
Version: 1.1.6
Summary: Nonebot2 Plugin Template
Author-Email: EnderKylin <3162176860@qq.com>
License: MIT
Requires-Python: >=3.9
Requires-Dist: aiohttp>=3.12.15
Requires-Dist: nonebot-adapter-onebot>=2.4.6
